{
  "products": [
    {
      "id": "mockup-branding-kit-01",
      "slug": "mockup-branding-kit-01",
      "title": "Premium Branding Kit Mockups",
      "subtitle": "Профессиональные мокапы для брендинга",
      "category": "mockups",
      "tags": ["figma", "photoshop", "branding", "ru", "en"],
      "badges": ["new", "best"],
      "compatibility": ["figma", "ps", "ai", "svg", "png"],
      "license_options": [
        {"type": "personal", "price_usd": 19},
        {"type": "commercial", "price_usd": 39},
        {"type": "extended", "price_usd": 99}
      ],
      "default_license": "commercial",
      "thumbnail": "/assets/store/mockup-branding-kit-01/thumb.webp",
      "gallery": [
        "/assets/store/mockup-branding-kit-01/1.webp",
        "/assets/store/mockup-branding-kit-01/2.webp",
        "/assets/store/mockup-branding-kit-01/3.webp",
        "/assets/store/mockup-branding-kit-01/demo.mp4"
      ],
      "whats_inside": [
        "15 mockups 4000×3000px",
        "PSD/Smart Objects",
        "Figma components",
        "Readme + EULA"
      ],
      "file_size_mb": 820,
      "archive_url": "https://lemonsqueezy.com/checkout/buy/12345",
      "version": "1.0.0",
      "last_update": "2025-01-20",
      "languages": ["ru", "en"],
      "short_description": "Набор профессиональных мокапов для презентации брендинга. Включает визитки, конверты, упаковку и цифровые носители.",
      "long_description_html": "<p>Premium Branding Kit Mockups — это профессиональный набор мокапов для презентации ваших брендинг-проектов. Включает 15 высококачественных мокапов в разрешении 4000×3000px.</p><p>Что входит в набор:</p><ul><li>Визитки (3 варианта)</li><li>Конверты и бланки</li><li>Упаковка товаров</li><li>Цифровые носители</li><li>Социальные сети</li></ul><p>Все файлы готовы к использованию в Photoshop, Figma и других дизайн-программах.</p>",
      "seo": {
        "title": "Купить Premium Branding Kit Mockups — Магазин Tiarkel",
        "description": "Профессиональные мокапы для брендинга. 15 высококачественных мокапов в разрешении 4000×3000px. Подходит для Photoshop, Figma.",
        "og_image": "/assets/store/mockup-branding-kit-01/og.webp"
      }
    },
    {
      "id": "ui-kit-modern-01",
      "slug": "ui-kit-modern-01",
      "title": "Modern UI Kit",
      "subtitle": "Современный UI-кит для веб-приложений",
      "category": "ui",
      "tags": ["figma", "ui", "web", "ru", "en"],
      "badges": ["new"],
      "compatibility": ["figma", "svg", "png"],
      "license_options": [
        {"type": "personal", "price_usd": 29},
        {"type": "commercial", "price_usd": 59},
        {"type": "extended", "price_usd": 149}
      ],
      "default_license": "commercial",
      "thumbnail": "/assets/store/ui-kit-modern-01/thumb.webp",
      "gallery": [
        "/assets/store/ui-kit-modern-01/1.webp",
        "/assets/store/ui-kit-modern-01/2.webp",
        "/assets/store/ui-kit-modern-01/3.webp"
      ],
      "whats_inside": [
        "50+ компонентов",
        "Figma components",
        "Auto-layout",
        "Design system"
      ],
      "file_size_mb": 45,
      "archive_url": "https://lemonsqueezy.com/checkout/buy/12346",
      "version": "1.0.0",
      "last_update": "2025-01-18",
      "languages": ["ru", "en"],
      "short_description": "Современный UI-кит с 50+ компонентами для создания веб-приложений. Включает полную систему дизайна.",
      "long_description_html": "<p>Modern UI Kit — это современный набор компонентов для создания веб-приложений. Включает более 50 готовых компонентов с auto-layout и полной системой дизайна.</p><p>Компоненты включают:</p><ul><li>Кнопки и формы</li><li>Навигация и меню</li><li>Карточки и списки</li><li>Модальные окна</li><li>Иконки и иллюстрации</li></ul>",
      "seo": {
        "title": "Купить Modern UI Kit — Магазин Tiarkel",
        "description": "Современный UI-кит с 50+ компонентами для веб-приложений. Figma components с auto-layout и design system.",
        "og_image": "/assets/store/ui-kit-modern-01/og.webp"
      }
    },
    {
      "id": "font-modern-sans-01",
      "slug": "font-modern-sans-01",
      "title": "Modern Sans Font Family",
      "subtitle": "Современная sans-serif гарнитура",
      "category": "fonts",
      "tags": ["font", "typography", "ru", "en"],
      "badges": ["best"],
      "compatibility": ["svg", "png", "universal"],
      "license_options": [
        {"type": "personal", "price_usd": 15},
        {"type": "commercial", "price_usd": 35},
        {"type": "extended", "price_usd": 89}
      ],
      "default_license": "commercial",
      "thumbnail": "/assets/store/font-modern-sans-01/thumb.webp",
      "gallery": [
        "/assets/store/font-modern-sans-01/1.webp",
        "/assets/store/font-modern-sans-01/2.webp"
      ],
      "whats_inside": [
        "4 начертания",
        "TTF, OTF, WOFF2",
        "Web fonts",
        "License PDF"
      ],
      "file_size_mb": 12,
      "archive_url": "https://lemonsqueezy.com/checkout/buy/12347",
      "version": "1.0.0",
      "last_update": "2025-01-15",
      "languages": ["ru", "en"],
      "short_description": "Современная sans-serif гарнитура с 4 начертаниями. Идеально подходит для веб-дизайна и печати.",
      "long_description_html": "<p>Modern Sans — это современная sans-serif гарнитура, созданная для веб-дизайна и печати. Включает 4 начертания: Light, Regular, Medium и Bold.</p><p>Особенности:</p><ul><li>Отличная читаемость</li><li>Поддержка кириллицы</li><li>Web-оптимизированные форматы</li><li>Множество языков</li></ul>",
      "seo": {
        "title": "Купить Modern Sans Font Family — Магазин Tiarkel",
        "description": "Современная sans-serif гарнитура с 4 начертаниями. Поддержка кириллицы, web-оптимизированные форматы.",
        "og_image": "/assets/store/font-modern-sans-01/og.webp"
      }
    },
    {
      "id": "icon-set-minimal-01",
      "slug": "icon-set-minimal-01",
      "title": "Minimal Icon Set",
      "subtitle": "Минималистичный набор иконок",
      "category": "icons",
      "tags": ["icons", "minimal", "ru", "en"],
      "badges": ["free"],
      "compatibility": ["svg", "png", "universal"],
      "license_options": [
        {"type": "personal", "price_usd": 0},
        {"type": "commercial", "price_usd": 9},
        {"type": "extended", "price_usd": 29}
      ],
      "default_license": "personal",
      "thumbnail": "/assets/store/icon-set-minimal-01/thumb.webp",
      "gallery": [
        "/assets/store/icon-set-minimal-01/1.webp",
        "/assets/store/icon-set-minimal-01/2.webp"
      ],
      "whats_inside": [
        "100+ иконок",
        "SVG, PNG 512px",
        "Figma components",
        "Free for personal use"
      ],
      "file_size_mb": 8,
      "archive_url": "https://lemonsqueezy.com/checkout/buy/12348",
      "version": "1.0.0",
      "last_update": "2025-01-10",
      "languages": ["ru", "en"],
      "short_description": "Минималистичный набор из 100+ иконок в стиле flat design. Бесплатно для личного использования.",
      "long_description_html": "<p>Minimal Icon Set — это набор из 100+ минималистичных иконок в стиле flat design. Идеально подходит для веб-сайтов, приложений и презентаций.</p><p>Включает:</p><ul><li>Иконки интерфейса</li><li>Социальные сети</li><li>Бизнес и финансы</li><li>Технологии</li><li>Образование</li></ul><p>Бесплатно для личного использования!</p>",
      "seo": {
        "title": "Скачать Minimal Icon Set — Магазин Tiarkel",
        "description": "Минималистичный набор из 100+ иконок в стиле flat design. Бесплатно для личного использования. SVG, PNG форматы.",
        "og_image": "/assets/store/icon-set-minimal-01/og.webp"
      }
    },
    {
      "id": "3d-product-mockup-01",
      "slug": "3d-product-mockup-01",
      "title": "3D Product Mockup Collection",
      "subtitle": "3D мокапы для презентации продуктов",
      "category": "3d",
      "tags": ["3d", "blender", "c4d", "ru", "en"],
      "badges": ["new"],
      "compatibility": ["blender", "c4d"],
      "license_options": [
        {"type": "personal", "price_usd": 25},
        {"type": "commercial", "price_usd": 49},
        {"type": "extended", "price_usd": 129}
      ],
      "default_license": "commercial",
      "thumbnail": "/assets/store/3d-product-mockup-01/thumb.webp",
      "gallery": [
        "/assets/store/3d-product-mockup-01/1.webp",
        "/assets/store/3d-product-mockup-01/2.webp",
        "/assets/store/3d-product-mockup-01/3.webp"
      ],
      "whats_inside": [
        "10 3D сцен",
        "Blender, C4D файлы",
        "Текстуры и материалы",
        "Рендер настройки"
      ],
      "file_size_mb": 450,
      "archive_url": "https://lemonsqueezy.com/checkout/buy/12349",
      "version": "1.0.0",
      "last_update": "2025-01-12",
      "languages": ["ru", "en"],
      "short_description": "Коллекция 3D мокапов для презентации продуктов. Включает 10 готовых сцен для Blender и Cinema 4D.",
      "long_description_html": "<p>3D Product Mockup Collection — это набор из 10 профессиональных 3D сцен для презентации продуктов. Все сцены готовы к рендеру и включают настройки освещения и материалов.</p><p>Включает:</p><ul><li>Упаковка товаров</li><li>Электроника</li><li>Косметика</li><li>Одежда и аксессуары</li><li>Мебель</li></ul>",
      "seo": {
        "title": "Купить 3D Product Mockup Collection — Магазин Tiarkel",
        "description": "Коллекция 3D мокапов для презентации продуктов. 10 готовых сцен для Blender и Cinema 4D с текстурами и материалами.",
        "og_image": "/assets/store/3d-product-mockup-01/og.webp"
      }
    },
    {
      "id": "lut-cinematic-01",
      "slug": "lut-cinematic-01",
      "title": "Cinematic LUT Pack",
      "subtitle": "Кинематографические LUT для видео",
      "category": "presets",
      "tags": ["lut", "video", "ae", "pr", "ru", "en"],
      "badges": ["best"],
      "compatibility": ["ae", "pr", "ps"],
      "license_options": [
        {"type": "personal", "price_usd": 12},
        {"type": "commercial", "price_usd": 25},
        {"type": "extended", "price_usd": 69}
      ],
      "default_license": "commercial",
      "thumbnail": "/assets/store/lut-cinematic-01/thumb.webp",
      "gallery": [
        "/assets/store/lut-cinematic-01/1.webp",
        "/assets/store/lut-cinematic-01/2.webp",
        "/assets/store/lut-cinematic-01/demo.mp4"
      ],
      "whats_inside": [
        "20 LUT файлов",
        "After Effects, Premiere",
        "Photoshop ACO",
        "Инструкция по установке"
      ],
      "file_size_mb": 15,
      "archive_url": "https://lemonsqueezy.com/checkout/buy/12350",
      "version": "1.0.0",
      "last_update": "2025-01-08",
      "languages": ["ru", "en"],
      "short_description": "Набор из 20 кинематографических LUT для создания профессионального видео. Совместим с After Effects, Premiere и Photoshop.",
      "long_description_html": "<p>Cinematic LUT Pack — это коллекция из 20 профессиональных LUT для создания кинематографического видео. Включает различные стили: драматический, романтический, документальный и другие.</p><p>Совместимость:</p><ul><li>After Effects</li><li>Premiere Pro</li><li>Photoshop</li><li>DaVinci Resolve</li></ul>",
      "seo": {
        "title": "Купить Cinematic LUT Pack — Магазин Tiarkel",
        "description": "Набор из 20 кинематографических LUT для профессионального видео. Совместим с After Effects, Premiere и Photoshop.",
        "og_image": "/assets/store/lut-cinematic-01/og.webp"
      }
    }
  ],
  "categories": [
    {
      "id": "mockups",
      "title": "Макеты",
      "description": "Профессиональные мокапы для презентации работ"
    },
    {
      "id": "templates",
      "title": "Шаблоны",
      "description": "Готовые шаблоны для различных проектов"
    },
    {
      "id": "fonts",
      "title": "Шрифты",
      "description": "Качественные шрифты для дизайна"
    },
    {
      "id": "icons",
      "title": "Иконки",
      "description": "Наборы иконок для интерфейсов"
    },
    {
      "id": "3d",
      "title": "3D-ассеты",
      "description": "3D модели и сцены"
    },
    {
      "id": "presets",
      "title": "LUT/Presets",
      "description": "LUT и пресеты для обработки"
    },
    {
      "id": "branding",
      "title": "Branding Kits",
      "description": "Готовые брендинг-киты"
    },
    {
      "id": "ui",
      "title": "UI-киты",
      "description": "Компоненты для интерфейсов"
    },
    {
      "id": "textures",
      "title": "Текстуры/Материалы",
      "description": "Текстуры для 3D и дизайна"
    },
    {
      "id": "other",
      "title": "Прочее",
      "description": "Другие цифровые товары"
    }
  ],
  "compatibility_tags": [
    {
      "id": "figma",
      "title": "Figma",
      "icon": "figma-icon.svg"
    },
    {
      "id": "ps",
      "title": "Photoshop",
      "icon": "photoshop-icon.svg"
    },
    {
      "id": "ai",
      "title": "Illustrator",
      "icon": "illustrator-icon.svg"
    },
    {
      "id": "ae",
      "title": "After Effects",
      "icon": "after-effects-icon.svg"
    },
    {
      "id": "pr",
      "title": "Premiere",
      "icon": "premiere-icon.svg"
    },
    {
      "id": "blender",
      "title": "Blender",
      "icon": "blender-icon.svg"
    },
    {
      "id": "c4d",
      "title": "Cinema 4D",
      "icon": "cinema4d-icon.svg"
    },
    {
      "id": "svg",
      "title": "SVG",
      "icon": "svg-icon.svg"
    },
    {
      "id": "png",
      "title": "PNG",
      "icon": "png-icon.svg"
    },
    {
      "id": "universal",
      "title": "Универсальные",
      "icon": "universal-icon.svg"
    }
  ]
} 